id3tree/__init__.py
id3tree/tree.py
id3tree-0.0.4.dist-info/LICENSE.txt
id3tree-0.0.4.dist-info/METADATA
id3tree-0.0.4.dist-info/WHEEL
id3tree-0.0.4.dist-info/top_level.txt
id3tree-0.0.4.dist-info/RECORD
