Metadata-Version: 2.1
Name: id3tree
Version: 0.0.4
Summary: This is used for creating multi-split entropy based ID3Trees.
Home-page: https://github.com/ragabala/Id3trees
Author: Ragavendran balakrishnan
Author-email: ragavendranb92@gmail.com
License: TEST
Platform: UNKNOWN
Classifier: Development Status :: 2 - Pre-Alpha
Classifier: Operating System :: POSIX :: Linux
Classifier: License :: Freeware
Classifier: Programming Language :: Python :: 2.7
Classifier: Programming Language :: Python :: 3.7
Requires-Dist: numpy
Requires-Dist: pandas
Provides-Extra: dev
Requires-Dist: pylint; extra == 'dev'
